Changelly/__init__.py
Changelly/changelly.py
changelly-0.11.dist-info/LICENSE.txt
changelly-0.11.dist-info/METADATA
changelly-0.11.dist-info/RECORD
changelly-0.11.dist-info/WHEEL
changelly-0.11.dist-info/top_level.txt
