Metadata-Version: 2.1
Name: changelly
Version: 0.11
Summary: Changelly Exchange API client
Home-page: https://github.com/codingsett/Changelly
Author: Joseph Kuria
Author-email: josephkiurire@gmail.com
License: GNU
Platform: UNKNOWN
